remina/__init__.py
remina/cache.py
remina/exceptions.py
remina/models.py
remina/configs/__init__.py
remina/configs/base.py
remina/configs/cache.py
remina/configs/embeddings.py
remina/configs/graph.py
remina/configs/llms.py
remina/configs/storage.py
remina/configs/vectors.py
remina/embeddings/__init__.py
remina/embeddings/base.py
remina/embeddings/gemini.py
remina/embeddings/openai.py
remina/graph/__init__.py
remina/graph/extraction.py
remina/graph/main.py
remina/graph/models.py
remina/graph/neo4j_store.py
remina/graph/prompts.py
remina/graph/search_utils.py
remina/graph/store.py
remina/graph/test_graph_search.py
remina/llms/__init__.py
remina/llms/base.py
remina/llms/gemini.py
remina/llms/openai.py
remina/memory/__init__.py
remina/memory/main.py
remina/memory/prompts.py
remina/memory/utils.py
remina/storage/__init__.py
remina/storage/base.py
remina/storage/mongodb.py
remina/storage/postgres.py
remina/storage/sqlite.py
remina/utils/__init__.py
remina/utils/factory.py
remina/vector_stores/__init__.py
remina/vector_stores/base.py
remina/vector_stores/chroma.py
remina/vector_stores/pinecone.py
remina/vector_stores/qdrant.py
remina-0.1.7.dist-info/licenses/LICENSE
remina-ts/node_modules/flatted/python/flatted.py
remina-0.1.7.dist-info/METADATA
remina-0.1.7.dist-info/WHEEL
remina-0.1.7.dist-info/top_level.txt
remina-0.1.7.dist-info/RECORD
