Metadata-Version: 2.4
Name: remina
Version: 0.1.7
Summary: Give your AI agents human-like memory. The pluggable memory layer for AI applications.
Author: @bikidsx
License: Apache-2.0
Project-URL: Homepage, https://github.com/bikidsx/remina
Project-URL: Documentation, https://docs.remina.dev
Project-URL: Repository, https://github.com/bikidsx/remina
Keywords: ai,memory,llm,agents,rag
Classifier: Development Status :: 3 - Alpha
Classifier: Intended Audience :: Developers
Classifier: License :: OSI Approved :: Apache Software License
Classifier: Programming Language :: Python :: 3
Classifier: Programming Language :: Python :: 3.10
Classifier: Programming Language :: Python :: 3.11
Classifier: Programming Language :: Python :: 3.12
Requires-Python: >=3.10
License-File: LICENSE
Requires-Dist: pydantic
Requires-Dist: openai
Requires-Dist: anthropic
Requires-Dist: google-genai
Requires-Dist: pinecone
Requires-Dist: asyncpg
Requires-Dist: psycopg[binary]
Requires-Dist: motor
Requires-Dist: redis
Requires-Dist: qdrant-client
Requires-Dist: chromadb
Requires-Dist: pgvector
Requires-Dist: aiosqlite
Provides-Extra: huggingface
Requires-Dist: sentence-transformers; extra == "huggingface"
Provides-Extra: ollama
Requires-Dist: ollama; extra == "ollama"
Provides-Extra: all
Requires-Dist: sentence-transformers; extra == "all"
Provides-Extra: dev
Requires-Dist: pytest; extra == "dev"
Requires-Dist: pytest-asyncio; extra == "dev"
Requires-Dist: pytest-cov; extra == "dev"
Requires-Dist: black; extra == "dev"
Requires-Dist: ruff; extra == "dev"
Requires-Dist: mypy; extra == "dev"
Dynamic: license-file
